aiohttp_spec.py
aiohttp_spec-0.1.0.dist-info/licenses/LICENSE
aiohttp_spec-0.1.0.dist-info/METADATA
aiohttp_spec-0.1.0.dist-info/WHEEL
aiohttp_spec-0.1.0.dist-info/top_level.txt
aiohttp_spec-0.1.0.dist-info/RECORD
