Metadata-Version: 2.4
Name: aiohttp-spec
Version: 0.1.0
Summary: Add your description here
Requires-Python: >=3.13
License-File: LICENSE
Requires-Dist: aiohttp>=3.12.15
Requires-Dist: jsonschema>=4.25.0
Dynamic: license-file
